{
	"수도권 지하철": "Seoul Metropolitan Subway",

	"1호선": "Line 1",
	"2호선": "LINE 2",
	"3호선": "LINE 3",
	"4호선": "LINE 4",
	"5호선": "LINE 5",
	"6호선": "LINE 6",
	"7호선": "LINE 7",
	"8호선": "LINE 8",
	"9호선": "LINE 9",
	"경의선": "GYEONGUI LINE",
	"경춘선": "GYEONCHUN LINE",
	"공항철도": "AIRPORT RAILROAD",
	"분당선": "BUNDANG LINE",
	"인천선": "INCHEON LINE",
	"중앙선": "JUNGANG LINE",
	"신분당선": "SHINBUNDANG LINE",
	"수인선": "SUIN LINE",

	"아차산": "Achasan",
	"애오개": "Aeogae",
	"아현": "Ahyeon",
	"공항시장": "Airport Market",
	"암사": "Amsa",
	"안암": "Anam",
	"안국": "Anguk",
	"아산": "Asan",
	"안산": "Ansan",
	"안양": "Anyang",
	"압구정": "Apgujeong",
	"압구정로데오": "Apgujeongrodeo",
	"예술회관": "Arts Center",
	"아신": "Asin",

	"지식정보단지": "BIT Zone",
	"배방": "Baebang",
	"백운": "Baegun",
	"백양리": "Baegyang-ri",
	"백석": "Baekseok",
	"백마": "Baengma",
	"박촌": "Bakchon",
	"발산": "Balsan",
	"방배": "Bangbae",
	"방학": "Banghak",
	"방화": "Banghwa",
	"방이": "Bangi",
	"반포": "Banpo",
	"반월": "Banwol",
	"범계": "Beomgye",
	"버티고개": "Beotigogae",
	"보정": "Bojeong",
	"복정": "Bokjeong",
	"보문": "Bomun",
	"봉천": "Bongcheon",
	"봉화산": "Bonghwasan",
	"봉명": "Bongmyeong",
	"보라매": "Boramae",
	"보산": "Bosan",
	"부천": "Bucheon",
	"부천시청": "Bucheon City Hall",
	"부천종합운동장": "Bucheon Stadium",
	"부개": "Bugae",
	"불광": "Bulgwang",
	"부평": "Bupyeong",
	"부평시장": "Bupyeong Market",
	"부평구청": "Bupyeong-gu Office",
	"부평삼거리": "Bupyeongsamgeori",
	"별내": "Byeollae",
	"병점": "Byeongjeom",

	"캠퍼스타운": "Campus Town",
	"센트럴파크": "Central Park",
	"창동": "Chang-dong",
	"창신": "Changsin",
	"철산": "Cheolsan",
	"천안": "Cheonan",
	"청담": "Cheongdam",
	"청구": "Cheonggu",
	"청계산입구": "Cheonggyesan",
	"청명": "Cheongmyeong",
	"청량리": "Cheongnyangni",
	"청평": "Cheongpyeong",
	"천호": "Cheonho",
	"천왕": "Cheonwang",
	"어린이대공원": "Children`s\nGrand\nPark",
	"초지": "Choji",
	"총신대": "Chongshin Univ.",
	"춘천": "Chuncheon",
	"충정로": "Chungjeongno",
	"충무로": "Chungmuro",
	"춘의": "Chunui",
	"시청": "City Hall",

	"대방": "Daebang",
	"대청": "Daecheong",
	"대치": "Daechi",
	"대곡": "Daegok",
	"대흥": "Daeheung",
	"대화": "Daehwa",
	"대모산입구": "Daemosan",
	"대림": "Daerim",
	"대성리": "Daeseong-ri",
	"대야미": "Daeyami",
	"단대오거리": "Dandaeogeori",
	"당고개": "Danggogae",
	"당정": "Dangjeong",
	"당산": "Dangsan",
	"답십리": "Dapsimni",
	"덕계": "Deokgye",
	"덕정": "Deokjeong",
	"덕소": "Deokso",
	"등촌": "Deungchon",
	"디지털미디어시티": "Digital\nMedia\nCity",
	"도봉": "Dobong",
	"도봉산": "Dobongsan",
	"도곡": "Dogok",
	"도화": "Dohwa",
	"독바위": "Dokbawi",
	"독산": "Doksan",
	"돌곶이": "Dolgoji",
	"동암": "Dongam",
	"동춘": "Dongchun",
	"동대문": "Dongdaemun",
	"동대문역사문화공원": "Dongdaemun History &\nCulture Park",
	"동두천": "Dongducheon",
	"동두천 중앙": "Dongducheon jungang",
	"동대입구": "Dongguk Univ.",
	"동인천": "Dongincheon",
	"동작": "Dongjak",
	"동막": "Dongmak",
	"동묘앞": "Dongmyo",
	"독립문": "Dongnimmun",
	"동수": "Dongsu",
	"도농": "Donong",
	"도림천": "Dorimcheon",
	"도심": "Dosim",
	"도원": "Dowon",
	"두정": "Dujeong",
	"둔촌동": "Dunchon-dong",

	"을지로입구": "Euljiro 1(il)-ga",
	"을지로3가": "Euljiro 3(sam)-ga",
	"을지로4가": "Euljiro 4(sa)-ga",
	"응암": "Eungam",
	"응봉": "Eungbong",
	"이대": "Ewha Womans Univ.",
	"고속터미널": "Express Bus Terminal",

	"가천대": "Gachon Univ.",
	"개봉": "Gaebong",
	"개화": "Gaehwa",
	"개화산": "Gaehwasan",
	"개포동": "Gaepo-dong",
	"개롱": "Gaerong",
	"가좌": "Gajwa",
	"갈매": "Galmae",
	"갈산": "Galsan",
	"가능": "Ganeung",
	"강변": "Gangbyeon",
	"강촌": "Gangchon",
	"강동": "Gangdong",
	"강동구청": "Gangdong-gu Office",
	"강남": "Gangnam",
	"강남구청": "Gangnam-gu Office",
	"간석오거리": "Ganseogogeori",
	"간석": "Ganseok",
	"가평": "Gapyeong",
	"가락시장": "Garak Market",
	"가산디지털단지": "Gasan\nDigital\nComplex",
	"가양": "Gayang",
	"검암": "Geomam",
	"거여": "Geoyeo",
	"금천구청": "Geumcheon-Gu Office",
	"금촌": "Geumchon",
	"금곡": "Geumgok",
	"금호": "Geumho",
	"금정": "Geumjeong",
	"금릉": "Geumneung",
	"기흥": "Giheung",
	"길동": "Gil-dong",
	"김포공항": "Gimpo Intl. Airport",
	"김유정": "Gimyujeong",
	"길음": "Gireum",
	"고덕": "Godeok",
	"고잔": "Gojan",
	"곡산": "Goksan",
	"공덕": "Gongdeok",
	"공릉": "Gongneung",
	"정부과천청사": "Government Complex Gwacheon",
	"구반포": "Gubanpo",
	"굽은다리": "Gubeundari",
	"구일": "Guil",
	"국수": "Guksu",
	"굴봉산": "Gulbongsan",
	"굴포천": "Gulpocheon",
	"군자": "Gunja",
	"군포": "Gunpo",
	"구파발": "Gupabal",
	"구리": "Guri",
	"구로": "Guro",
	"구로디지털단지": "Guro\nDigital\nComplex",
	"구룡": "Guryong",
	"구산": "Gusan",
	"구성": "Guseong",
	"구의": "Guui",
	"과천": "Gwacheon",
	"관악": "Gwanak",
	"광흥창": "Gwangheungchang",
	"광화문": "Gwanghwamun",
	"광명": "Gwangmyeong",
	"광명사거리": "Gwangmyeongsageori",
	"광나루": "Gwangnaru",
	"경인교대입구": "Gyeong-in Nat`l\nUniv. of\nEducation",
	"경복궁": "Gyeongbokgung",
	"계산": "Gyesan",
	"계양": "Gyeyang",
	"귤현": "Gyulhyeon",

	"행당": "Haengdang",
	"행신": "Haengsin",
	"하계": "Hagye",
	"학동": "Hak-dong",
	"한강진": "Hangangjin",
	"학여울": "Hangnyeoul",
	"외대앞": "Hankuk Univ. of Foreign Studies",
	"한남": "Hannam",
	"한성대입구": "Hansung Univ.",
	"한티": "Hanti",
	"한양대": "Hanyang Univ.",
	"한대앞": "Hanyang Univ. at Ansan",
	"합정": "Hapjeong",
	"흑석(중앙대입구)": "Heukseok",
	"회기": "Hoegi",
	"회현": "Hoehyeon",
	"회룡": "Hoeryong",
	"호구포": "Hogupo",
	"홍대입구": "Hongik Univ.",
	"홍제": "Hongje",
	"화곡": "Hwagok",
	"화전": "Hwajeon",
	"화정": "Hwajeong",
	"화랑대": "Hwarangdae",
	"화서": "Hwaseo",
	"혜화": "Hyehwa",
	"효창공원앞": "Hyochang park",

	"이촌": "Ichon",
	"일산": "Ilsan",
	"이매": "Imae",
	"임학": "Imhak",
	"인천": "Incheon",
	"인천터미널": "Incheon Bus Terminal",
	"인천시청": "Incheon City Hall",
	"인천국제공항": "Incheon Intl. Airport",
	"공항화물청사": "Incheon Intl. Airport Cargo Terminal",
	"인천대입구": "Incheon Nat'l Univ.",
	"인천논현": "Incheon Nonhyeon",
	"인덕원": "Indeogwon",
	"국제업무지구": "Intl. Business District",
	"일원": "Irwon",
	"이수": "Isu",
	"이태원": "Itaewon",

	"작전": "Jakjeon",
	"잠실": "Jamsil",
	"잠실나루": "Jamsillaru",
	"잠원": "Jamwon",
	"장암": "Jangam",
	"장한평": "Janghanpyeong",
	"장지": "Jangji",
	"장승배기": "Jangseungbaegi",
	"제기동": "Jegi-dong",
	"제물포": "Jemulpo",
	"정발산": "Jeongbalsan",
	"정자": "Jeongja",
	"정왕": "Jeongwang",
	"증미": "Jeungmi",
	"증산": "Jeungsan",
	"지축": "Jichuk",
	"지행": "Jihaeng",
	"지제": "Jije",
	"직산": "Jiksan",
	"진위": "Jinwi",
	"종각": "Jonggak",
	"종로3가": "Jongno 3(sam)-ga",
	"종로5가": "Jongno 5(o)-ga",
	"주안": "Juan",
	"죽전": "Jukjeon",
	"중동": "Jung-dong",
	"중앙": "Jungang",
	"중곡": "Junggok",
	"중계": "Junggye",
	"중화": "Junghwa",
	"중랑": "Jungnang",
	"주엽": "Juyeop",

	"까치산": "Kkachisan",
	"까치울": "Kkachiul",
	"건대입구": "Konkuk Univ.",
	"고려대": "Korea Univ.",
	"광운대": "Kwangwoon Univ.",

	"마천": "Macheon",
	"마들": "Madeul",
	"마두": "Madu",
	"매봉": "Maebong",
	"마곡": "Magok",
	"마장": "Majang",
	"망포": "Mangpo",
	"망우": "Mangu",
	"망월사": "Mangwolsa",
	"망원": "Mangwon",
	"마포": "Mapo",
	"마포구청": "Mapo-gu Office",
	"마석": "Maseok",
	"먹골": "Meokgol",
	"미아": "Mia",
	"미아삼거리": "Miasamgeori",
	"미금": "Migeum",
	"목동": "Mok-dong",
	"몽촌토성": "Mongchontoseong",
	"모란": "Moran",
	"무악재": "Muakjae",
	"문래": "Mullae",
	"문학경기장": "Munhak Sports Complex",
	"문정": "Munjeong",
	"문산": "Munsan",
	"명동": "Myeong-dong",
	"명학": "Myeonghak",
	"명일": "Myeongil",
	"면목": "Myeonmok",

	"내방": "Naebang",
	"낙성대": "Nakseongdae",
	"남부터미널": "Nambu Bus Terminal",
	"남춘천": "Namchuncheon",
	"남동인더스파크": "Namdong Induspark",
	"남구로": "Namguro",
	"남한산성입구": "Namhansanseong",
	"남성": "Namseong",
	"남태령": "Namtaeryeong",
	"남영": "Namyeong",
	"국회의사당": "National Assembly",
	"경찰병원": "National Police Hospital",
	"능곡": "Neunggok",
	"노들": "Nodeul",
	"녹양": "Nogyang",
	"녹번": "Nokbeon",
	"녹천": "Nokcheon",
	"녹사평": "Noksapyeong",
	"논현": "Nonhyeon",
	"노량진": "Noryangjin",
	"노원": "Nowon",

	"오빈": "Obin",
	"오금": "Ogeum",
	"오이도": "Oido",
	"옥수": "Oksu",
	"올림픽공원": "Olympic Park",
	"오목교": "Omokgyo",
	"온수": "Onsu",
	"온양온천": "Onyang oncheon",
	"오리": "Ori",
	"오류동": "Oryu-dong",
	"오산": "Osan",
	"오산대": "Osan College",

	"파주": "Paju",
	"팔당": "Paldang",
	"판교": "Pangyo",
	"풍산": "Pungsan",
	"평촌": "Pyeongchon",
	"평내호평": "PyeongnaeHopyeong",
	"평택": "Pyeongtaek",

	"사당": "Sadang",
	"사평": "Sapyeong",
	"새절": "Saejeol",
	"샛강": "Saetgang",
	"사가정": "Sagajeong",
	"삼각지": "Samgakji",
	"삼산체육관": "Samsan Gymnasium",
	"삼성": "Samseong",
	"삼송": "Samsong",
	"산본": "Sanbon",
	"상동": "Sang-dong",
	"상봉": "Sangbong",
	"상천": "Sangcheon",
	"상도": "Sangdo",
	"상갈": "Sanggal",
	"상계": "Sanggye",
	"상일동": "Sangil-dong",
	"상록수": "Sangnoksu",
	"상수": "Sangsu",
	"상왕십리": "Sangwangsimni",
	"상월곡": "Sangwolgok",
	"산성": "Sanseong",
	"사릉": "Sareung",
	"세마": "Sema",
	"서빙고": "Seobinggo",
	"서초": "Seocho",
	"서대문": "Seodaemun",
	"서동탄": "Seodongtan",
	"서현": "Seohyeon",
	"서정리": "Seojeong-ri",
	"석촌": "Seokchon",
	"석계": "Seokgye",
	"석수": "Seoksu",
	"선릉": "Seolleung",
	"선바위": "Seonbawi",
	"성환": "Seonghwan",
	"성수": "Seongsu",
	"선학": "Seonhak",
	"선정릉": "Seonjeongneung",
	"선유도": "Seonyudo",
	"대공원": "Seoul Grand Park",
	"서울대입구": "Seoul Nat`l Univ.",
	"교대": "Seoul Nat`l Univ. of Education",
	"경마공원": "Seoul Racecourse Park",
	"서울역": "Seoul Station",
	"서울숲": "Seoul-forest",
	"세류": "Seryu",
	"신림": "Sillim",
	"신방화": "Sinbanghwa",
	"신반포": "Sinbanpo",
	"신창(순천향대)": "Sinchang(Soonchunhyang Univ.)",
	"신천": "Sincheon",
	"신촌": "Sinchon",
	"신촌(경의선)": "Sinchon",
	"신대방": "Sindaebang",
	"신대방삼거리": "Sindaebangsamgeori",
	"신당": "Sindang",
	"신답": "Sindap",
	"신도림": "Sindorim",
	"신갈": "Singal",
	"신금호": "Singeumho",
	"신길": "Singil",
	"신길온천": "Singil oncheon",
	"신흥": "Sinheung",
	"신이문": "Sinimun",
	"신정": "Sinjeong",
	"신정네거리": "Sinjeongnegeori",
	"신중동": "Sinjung-dong",
	"신목동": "Sinmokdong",
	"신논현": "Sinnonhyeon",
	"신풍": "Sinpung",
	"신사": "Sinsa",
	"신설동": "Sinseol-dong",
	"신원": "Sinwon",
	"신연수": "Sinyeonsu",
	"신용산": "Sinyongsan",
	"서강": "Sogang Univ.",
	"송도": "Songdo",
	"송정": "Songjeong",
	"송내": "Songnae",
	"송파": "Songpa",
	"송탄": "Songtan",
	"숙대입구": "Sookmyung Women`s Univ.",
	"숭실대입구": "Soongsil Univ.",
	"소래포구": "Soraepogu",
	"소사": "Sosa",
	"소요산": "Soyosan",
	"종합운동장": "Sports Complex",
	"쌍문": "Ssangmun",
	"쌍용(나사렛대)": "Ssangyong(Korea Nazarene Univ.)",
	"수진": "Sujin",
	"수내": "Sunae",
	"성균관대": "Sungkyunkwan Univ.",
	"성신여대입구": "Sungshin Women`s Univ.",
	"수락산": "Suraksan",
	"수리산": "Surisan",
	"수색": "Susaek",
	"수서": "Suseo",
	"수원": "Suwon",
	"수유": "Suyu",

	"태평": "Taepyeong",
	"태릉입구": "Taereung",
	"탄현": "Tanhyeon",
	"테크노파크": "Technopark",
	"퇴계원": "Toegyewon",
	"뚝섬": "Ttukseom",
	"뚝섬유원지": "Ttukseom Resort",

	"의정부": "Uijeongbu",
	"의왕": "Uiwang",
	"우장산": "Ujangsan",
	"운길산": "Ungilsan",
	"운정": "Unjeong",
	"운서": "Unseo",

	"왕십리": "Wangsimni",
	"월곡": "Wolgok",
	"월곶": "Wolgot",
	"월계": "Wolgye",
	"월롱": "Wollong",
	"원당": "Wondang",
	"원덕": "Wondeok",
	"원인재": "Woninjae",
	"월드컵경기장": "World Cup Stadium",

	"약수": "Yaksu",
	"양천향교": "Yangcheon Hyanggyo",
	"양천구청": "Yangcheon-gu Office",
	"양재": "Yangjae",
	"양재시민의숲": "Yangjae Citizen's Forest",
	"양정": "Yangjeong",
	"양주": "Yangju",
	"양평": "Yangpyeong",
	"양수": "Yangsu",
	"양원": "Yangwon",
	"야탑": "Yatap",
	"역촌": "Yeokchon",
	"역곡": "Yeokgok",
	"역삼": "Yeoksam",
	"염창": "Yeomchang",
	"영등포": "Yeongdeungpo",
	"영등포시장": "Yeongdeungpo Market",
	"영등포구청": "Yeongdeungpo-gu Office",
	"영통": "Yeongtong",
	"연신내": "Yeonsinnae",
	"연수": "Yeonsu",
	"여의도": "Yeouido",
	"여의나루": "Yeouinaru",
	"용답": "Yongdap",
	"용두": "Yongdu",
	"용마산": "Yongmasan",
	"용문": "Yongmun",
	"용산": "Yongsan"
}